heatfall/__init__.py
heatfall/heat.py
heatfall-0.1.0.dist-info/LICENSE
heatfall-0.1.0.dist-info/METADATA
heatfall-0.1.0.dist-info/WHEEL
heatfall-0.1.0.dist-info/top_level.txt
heatfall-0.1.0.dist-info/RECORD
