Metadata-Version: 2.1
Name: heatfall
Version: 0.1.0
Summary: Easy to use functions to plot heat maps of geospatial data using staticmaps.
Author: Odos Matthews
License: MIT
Platform: unix
Platform: linux
Platform: osx
Platform: cygwin
Platform: win32
Classifier: Programming Language :: Python :: 3
Classifier: Programming Language :: Python :: 3 :: Only
Classifier: Programming Language :: Python :: 3.8
Classifier: Programming Language :: Python :: 3.9
Classifier: Programming Language :: Python :: 3.10
Requires-Python: >=3.8
License-File: LICENSE
Requires-Dist: range-key-dict
Requires-Dist: geodude
Requires-Dist: py-staticmaps
Requires-Dist: Pillow (<=9.5.0)
Requires-Dist: more-itertools
Requires-Dist: tinytim
Requires-Dist: h3
Provides-Extra: testing
Requires-Dist: mypy (>=0.910) ; extra == 'testing'
Requires-Dist: flake8 (>=3.9) ; extra == 'testing'
Requires-Dist: tox (>=3.24) ; extra == 'testing'
Requires-Dist: pytest (==6.2.5) ; extra == 'testing'
Requires-Dist: pytest-cov (==2.12.1) ; extra == 'testing'
